MANIFEST.in
README.txt
setup.cfg
setup.py
adminactionview/__init__.py
adminactionview/forms.py
adminactionview/views.py
adminactionview.egg-info/PKG-INFO
adminactionview.egg-info/SOURCES.txt
adminactionview.egg-info/dependency_links.txt
adminactionview.egg-info/not-zip-safe
adminactionview.egg-info/top_level.txt
adminactionview/templates/adminactionview/base.html