Metadata-Version: 1.0
Name: adminactionview
Version: 0.2
Summary: Add an intermediate page to the django admin when preforming actions. Here you can define extra parameters for your action
Home-page: https://github.com/MichielDePaepe/adminactionview
Author: Michiel De Paepe
Author-email: michiel.de.paepe@gmail.com
License: MIT licence, see LICENCE.txt
Platform: UNKNOWN
